<level>
	<name></name>

	<weapon>/weapon/shock2.xml</weapon>

	<effects>
		<effect>
			<visual>
				<material>/material/tex-ac.xml</material>
				<texstage>/texture/level/space4.jpg</texstage>
				<mesh>/mesh/bg.xml</mesh>
			</visual>
			<xposition>0.0</xposition>
			<yposition>0.0</yposition>
			<zposition>1600.0</zposition>
			<xscale>5.1</xscale>
			<yscale>5.1</yscale>
			<zscale>5.1</zscale>
		</effect>

		<effect>
			<name>planet</name>
			<visual>
				<material>/material/tex-ac.xml</material>
				<texstage>/texture/planets/blue01.png</texstage>
				<mesh>/mesh/centered-512x512.xml</mesh>
			</visual>
			<xposition>-500.0</xposition>
			<yposition>-500.0</yposition>
			<zposition>0.0</zposition>
			<orbit>
				<speed>0.1</speed>
				<xaxis>1.0</xaxis>
				<yaxis>-1.0</yaxis>
				<zaxis>-0.5</zaxis>
				<xcenter>0.0</xcenter>
				<ycenter>0.0</ycenter>
				<zcenter>0.0</zcenter>
			</orbit>
		</effect>
	</effects>

	<!-- all time -->
	<schedule>
		<object>/object/terran1-big1.xml</object>
		<begintime>0</begintime>
		<endtime>130000</endtime>
		<count>30</count>
		<orbitradius>500.0</orbitradius>
		<targeted/>
		<shard>/object/bonus/capsule1.xml</shard>
		<shardcount>30</shardcount>
	</schedule>

	<!-- wave 06 -->
	<schedule>
		<object>/object/mine1-small1.xml</object>
		<begintime>0</begintime>
		<endtime>200</endtime>
		<count>10</count>
		<orbitradius>300.0</orbitradius>
		<zoom/>
		<shard>/object/bonus/cask-red.xml</shard>
		<shardcount>5</shardcount>
	</schedule>
	<schedule>
		<object>/object/mine1-small2.xml</object>
		<begintime>400</begintime>
		<endtime>600</endtime>
		<count>8</count>
		<orbitradius>280.0</orbitradius>
		<zoom/>
		<shard>/object/bonus/cask-yellow.xml</shard>
		<shardcount>5</shardcount>
	</schedule>
	<schedule>
		<object>/object/mine1-small3.xml</object>
		<begintime>800</begintime>
		<endtime>1000</endtime>
		<count>6</count>
		<orbitradius>260.0</orbitradius>
		<zoom/>
	</schedule>

	<schedule>
		<object>/object/terran1-small1.xml</object>
		<begintime>0</begintime>
		<endtime>20000</endtime>
		<count>30</count>
		<orbitradius>500.0</orbitradius>
		<targeted/>
		<shard>/object/bonus/cask-yellow.xml</shard>
		<shardcount>5</shardcount>
	</schedule>
	<schedule>
		<object>/object/ufo1-small2.xml</object>
		<begintime>0</begintime>
		<endtime>20000</endtime>
		<count>40</count>
		<orbitradius>500.0</orbitradius>
		<shard>/object/bonus/cask-red.xml</shard>
		<shardcount>5</shardcount>
	</schedule>
	<schedule>
		<object>/object/terran1-small2.xml</object>
		<begintime>0</begintime>
		<endtime>20000</endtime>
		<count>20</count>
		<orbitradius>500.0</orbitradius>
		<targeted/>
		<shard>/object/bonus/cask-green.xml</shard>
		<shardcount>5</shardcount>
	</schedule>

	<!-- wave 07 -->
	<schedule>
		<object>/object/terran1-small1.xml</object>
		<begintime>20000</begintime>
		<endtime>40000</endtime>
		<count>40</count>
		<orbitradius>500.0</orbitradius>
		<targeted/>
		<shard>/object/bonus/box1.xml</shard>
		<shardcount>10</shardcount>
	</schedule>
	<schedule>
		<object>/object/ufo1-big1.xml</object>
		<begintime>20000</begintime>
		<endtime>40000</endtime>
		<count>30</count>
		<orbitradius>500.0</orbitradius>
		<shard>/object/bonus/cask-yellow.xml</shard>
		<shardcount>5</shardcount>
	</schedule>
	<schedule>
		<object>/object/ufo1-small2.xml</object>
		<begintime>20000</begintime>
		<endtime>40000</endtime>
		<count>20</count>
		<orbitradius>500.0</orbitradius>
		<shard>/object/bonus/cask-green.xml</shard>
		<shardcount>5</shardcount>
	</schedule>
	<schedule>
		<object>/object/terran1-small2.xml</object>
		<begintime>20000</begintime>
		<endtime>40000</endtime>
		<count>20</count>
		<orbitradius>500.0</orbitradius>
		<targeted/>
		<shard>/object/bonus/cask-red.xml</shard>
		<shardcount>5</shardcount>
	</schedule>

	<!-- wave 08 -->
	<schedule>
		<object>/object/mine1-small1.xml</object>
		<begintime>45000</begintime>
		<endtime>46000</endtime>
		<count>15</count>
		<orbitradius>300.0</orbitradius>
		<zoom/>
		<shard>/object/bonus/cask-red.xml</shard>
		<shardcount>3</shardcount>
	</schedule>
	<schedule>
		<object>/object/mine1-small2.xml</object>
		<begintime>47000</begintime>
		<endtime>48000</endtime>
		<count>13</count>
		<orbitradius>230.0</orbitradius>
		<zoom/>
		<shard>/object/bonus/cask-yellow.xml</shard>
		<shardcount>3</shardcount>
	</schedule>
	<schedule>
		<object>/object/mine1-small3.xml</object>
		<begintime>49000</begintime>
		<endtime>50000</endtime>
		<count>10</count>
		<orbitradius>160.0</orbitradius>
		<zoom/>
	</schedule>

	<schedule>
		<object>/object/terran1-small1.xml</object>
		<begintime>40000</begintime>
		<endtime>60000</endtime>
		<count>15</count>
		<orbitradius>500.0</orbitradius>
		<targeted/>
		<shard>/object/bonus/box1.xml</shard>
		<shardcount>5</shardcount>
	</schedule>
	<schedule>
		<object>/object/ufo1-big1.xml</object>
		<begintime>40000</begintime>
		<endtime>60000</endtime>
		<count>10</count>
		<orbitradius>500.0</orbitradius>
	</schedule>
	<schedule>
		<object>/object/ufo1-small2.xml</object>
		<begintime>40000</begintime>
		<endtime>60000</endtime>
		<count>10</count>
		<orbitradius>500.0</orbitradius>
	</schedule>
	<schedule>
		<object>/object/terran1-small2.xml</object>
		<begintime>40000</begintime>
		<endtime>60000</endtime>
		<count>10</count>
		<orbitradius>500.0</orbitradius>
		<targeted/>
		<shard>/object/bonus/cask-red.xml</shard>
		<shardcount>3</shardcount>
	</schedule>

	<!-- wave 09 -->
	<schedule>
		<object>/object/terran1-small1.xml</object>
		<begintime>40000</begintime>
		<endtime>60000</endtime>
		<count>35</count>
		<orbitradius>500.0</orbitradius>
		<targeted/>
		<shard>/object/bonus/box1.xml</shard>
		<shardcount>5</shardcount>
	</schedule>
	<schedule>
		<object>/object/ufo1-big1.xml</object>
		<begintime>40000</begintime>
		<endtime>60000</endtime>
		<count>20</count>
		<orbitradius>500.0</orbitradius>
	</schedule>
	<schedule>
		<object>/object/ufo1-small2.xml</object>
		<begintime>40000</begintime>
		<endtime>60000</endtime>
		<count>10</count>
		<orbitradius>500.0</orbitradius>
	</schedule>
	<schedule>
		<object>/object/terran1-small2.xml</object>
		<begintime>40000</begintime>
		<endtime>60000</endtime>
		<count>10</count>
		<orbitradius>500.0</orbitradius>
		<targeted/>
		<shard>/object/bonus/cask-red.xml</shard>
		<shardcount>2</shardcount>
	</schedule>

	<!-- wave 10 -->
	<schedule>
		<object>/object/mine1-small3.xml</object>
		<begintime>70000</begintime>
		<endtime>71000</endtime>
		<count>9</count>
		<orbitradius>300.0</orbitradius>
		<zoom/>
		<shard>/object/bonus/cask-red.xml</shard>
		<shardcount>1</shardcount>
	</schedule>
	<schedule>
		<object>/object/mine1-small3.xml</object>
		<begintime>72000</begintime>
		<endtime>73000</endtime>
		<count>7</count>
		<orbitradius>240.0</orbitradius>
		<zoom/>
		<shard>/object/bonus/cask-yellow.xml</shard>
		<shardcount>1</shardcount>
	</schedule>
	<schedule>
		<object>/object/mine1-small3.xml</object>
		<begintime>74000</begintime>
		<endtime>75000</endtime>
		<count>5</count>
		<orbitradius>180.0</orbitradius>
		<zoom/>
	</schedule>

	<schedule>
		<object>/object/terran1-small1.xml</object>
		<begintime>60000</begintime>
		<endtime>80000</endtime>
		<count>30</count>
		<orbitradius>500.0</orbitradius>
		<targeted/>
		<shard>/object/bonus/box1.xml</shard>
		<shardcount>5</shardcount>
	</schedule>
	<schedule>
		<object>/object/ufo1-big1.xml</object>
		<begintime>60000</begintime>
		<endtime>80000</endtime>
		<count>10</count>
		<orbitradius>500.0</orbitradius>
	</schedule>
	<schedule>
		<object>/object/ufo1-small2.xml</object>
		<begintime>60000</begintime>
		<endtime>80000</endtime>
		<count>5</count>
		<orbitradius>500.0</orbitradius>
	</schedule>
	<schedule>
		<object>/object/terran1-small2.xml</object>
		<begintime>60000</begintime>
		<endtime>80000</endtime>
		<count>10</count>
		<orbitradius>500.0</orbitradius>
		<targeted/>
		<shard>/object/bonus/cask-red.xml</shard>
		<shardcount>1</shardcount>
	</schedule>

</level>
